xw_cbase.cpython-39-darwin.so
xw_cbase-16.1.1.dist-info/RECORD
xw_cbase-16.1.1.dist-info/LICENSE
xw_cbase-16.1.1.dist-info/WHEEL
xw_cbase-16.1.1.dist-info/top_level.txt
xw_cbase-16.1.1.dist-info/METADATA
