Metadata-Version: 2.1
Name: xw-cbase
Version: 16.1.1
Summary: utils for xw
Home-page: https://www.xwodoo.com/
Author: xw odoo
Author-email: 2243879204@qq.com
Requires-Python: >=3.7
License-File: LICENSE
